ebilling_postfinance/__init__.py
ebilling_postfinance/ebilling_postfinance.py
ebilling_postfinance/certificates/inte/SwissSign_EV_Gold_CA_2014-G22.cer
ebilling_postfinance/certificates/inte/SwissSign_Gold_CA-G2.cer
ebilling_postfinance/certificates/inte/ebill-ki.postfinance.ch.cer
ebilling_postfinance/certificates/prod/SwissSign_EV_Gold_CA_2014-G22.cer
ebilling_postfinance/certificates/prod/SwissSign_Gold_CA-G2.cer
ebilling_postfinance/certificates/prod/ebill.postfinance.ch.cer
ebilling_postfinance/wsdl/b2bservice_inte.wsdl
ebilling_postfinance/wsdl/b2bservice_prod.wsdl
ebilling_postfinance-0.1.1.dist-info/METADATA
ebilling_postfinance-0.1.1.dist-info/WHEEL
ebilling_postfinance-0.1.1.dist-info/top_level.txt
ebilling_postfinance-0.1.1.dist-info/RECORD
